{
  "testcases": [
    {
      "testcase": [
        {
          "receiver": "ue",
          "name": "enable_vowifi",
          "reporter": "epdg",
          "id": "update-401_unauthorized-www_authenticate-nonce-median-1"
        },
        {
          "receiver": "epdg",
          "name": "ike_sa_init_response",
          "reporter": "epdg"
        },
        {
          "receiver": "epdg",
          "name": "ike_auth_1_response",
          "reporter": "epdg"
        },
        {
          "receiver": "epdg",
          "name": "ike_auth_2_response",
          "reporter": "epdg"
        },
        {
          "receiver": "epdg",
          "name": "ike_auth_3_response",
          "reporter": "ims"
        },
        {
          "receiver": "ims",
          "name": "401_unauthorized",
          "reporter": "ims",
          "sub": [
            {
              "name": "www_authenticate",
              "sub": [
                {
                  "name": "nonce",
                  "op": "update",
                  "type": "string",
                  "value": "median"
                }
              ]
            }
          ]
        }
      ]
    }
  ]
}
