{
  "testcases": [
    {
      "testcase": [
        {
          "receiver": "ue",
          "name": "enable_vowifi",
          "reporter": "epdg",
          "id": "replay-401_unauthorized-www_authenticate-nonce-1"
        },
        {
          "receiver": "epdg",
          "name": "ike_sa_init_response",
          "reporter": "epdg"
        },
        {
          "receiver": "epdg",
          "name": "ike_auth_1_response",
          "reporter": "epdg"
        },
        {
          "receiver": "epdg",
          "name": "ike_auth_2_response",
          "reporter": "epdg"
        },
        {
          "receiver": "epdg",
          "name": "ike_auth_3_response",
          "reporter": "ims"
        },
        {
          "receiver": "ims",
          "name": "401_unauthorized",
          "reporter": "ims",
          "sub": [
            {
              "name": "www_authenticate",
              "sub": [
                {
                  "name": "nonce",
                  "op": "update",
                  "type": "string",
                  "value": 0
                }
              ]
            }
          ]
        },
        {
          "receiver": "ims",
          "name": "401_unauthorized",
          "reporter": "ims",
          "sub": [
            {
              "name": "www_authenticate",
              "sub": [
                {
                  "name": "nonce",
                  "op": "update",
                  "type": "string",
                  "value": 0
                }
              ]
            },
            {
              "name": "message_id",
              "type": "string",
              "value": "previous"
            }
          ],
          "op": "replay"
        }
      ]
    },
    {
      "testcase": [
        {
          "receiver": "ue",
          "name": "enable_vowifi",
          "reporter": "epdg",
          "id": "replay-401_unauthorized-www_authenticate-algorithm-1"
        },
        {
          "receiver": "epdg",
          "name": "ike_sa_init_response",
          "reporter": "epdg"
        },
        {
          "receiver": "epdg",
          "name": "ike_auth_1_response",
          "reporter": "epdg"
        },
        {
          "receiver": "epdg",
          "name": "ike_auth_2_response",
          "reporter": "epdg"
        },
        {
          "receiver": "epdg",
          "name": "ike_auth_3_response",
          "reporter": "ims"
        },
        {
          "receiver": "ims",
          "name": "401_unauthorized",
          "reporter": "ims",
          "sub": [
            {
              "name": "www_authenticate",
              "sub": [
                {
                  "name": "algorithm",
                  "op": "update",
                  "type": "string",
                  "value": 0
                }
              ]
            }
          ]
        },
        {
          "receiver": "ims",
          "name": "401_unauthorized",
          "reporter": "ims",
          "sub": [
            {
              "name": "www_authenticate",
              "sub": [
                {
                  "name": "algorithm",
                  "op": "update",
                  "type": "string",
                  "value": 0
                }
              ]
            },
            {
              "name": "message_id",
              "type": "string",
              "value": "previous"
            }
          ],
          "op": "replay"
        }
      ]
    },
    {
      "testcase": [
        {
          "receiver": "ue",
          "name": "enable_vowifi",
          "reporter": "epdg",
          "id": "replay-401_unauthorized-security_server-alg-1"
        },
        {
          "receiver": "epdg",
          "name": "ike_sa_init_response",
          "reporter": "epdg"
        },
        {
          "receiver": "epdg",
          "name": "ike_auth_1_response",
          "reporter": "epdg"
        },
        {
          "receiver": "epdg",
          "name": "ike_auth_2_response",
          "reporter": "epdg"
        },
        {
          "receiver": "epdg",
          "name": "ike_auth_3_response",
          "reporter": "ims"
        },
        {
          "receiver": "ims",
          "name": "401_unauthorized",
          "reporter": "ims",
          "sub": [
            {
              "name": "security_server",
              "sub": [
                {
                  "name": "alg",
                  "op": "update",
                  "type": "string",
                  "value": 0
                }
              ]
            }
          ]
        },
        {
          "receiver": "ims",
          "name": "401_unauthorized",
          "reporter": "ims",
          "sub": [
            {
              "name": "security_server",
              "sub": [
                {
                  "name": "alg",
                  "op": "update",
                  "type": "string",
                  "value": 0
                }
              ]
            },
            {
              "name": "message_id",
              "type": "string",
              "value": "previous"
            }
          ],
          "op": "replay"
        }
      ]
    },
    {
      "testcase": [
        {
          "receiver": "ue",
          "name": "enable_vowifi",
          "reporter": "epdg",
          "id": "replay-401_unauthorized-security_server-ealg-1"
        },
        {
          "receiver": "epdg",
          "name": "ike_sa_init_response",
          "reporter": "epdg"
        },
        {
          "receiver": "epdg",
          "name": "ike_auth_1_response",
          "reporter": "epdg"
        },
        {
          "receiver": "epdg",
          "name": "ike_auth_2_response",
          "reporter": "epdg"
        },
        {
          "receiver": "epdg",
          "name": "ike_auth_3_response",
          "reporter": "ims"
        },
        {
          "receiver": "ims",
          "name": "401_unauthorized",
          "reporter": "ims",
          "sub": [
            {
              "name": "security_server",
              "sub": [
                {
                  "name": "ealg",
                  "op": "update",
                  "type": "string",
                  "value": 0
                }
              ]
            }
          ]
        },
        {
          "receiver": "ims",
          "name": "401_unauthorized",
          "reporter": "ims",
          "sub": [
            {
              "name": "security_server",
              "sub": [
                {
                  "name": "ealg",
                  "op": "update",
                  "type": "string",
                  "value": 0
                }
              ]
            },
            {
              "name": "message_id",
              "type": "string",
              "value": "previous"
            }
          ],
          "op": "replay"
        }
      ]
    },
    {
      "testcase": [
        {
          "receiver": "ue",
          "name": "enable_vowifi",
          "reporter": "epdg",
          "id": "update-401_unauthorized-www_authenticate-nonce-random-1"
        },
        {
          "receiver": "epdg",
          "name": "ike_sa_init_response",
          "reporter": "epdg"
        },
        {
          "receiver": "epdg",
          "name": "ike_auth_1_response",
          "reporter": "epdg"
        },
        {
          "receiver": "epdg",
          "name": "ike_auth_2_response",
          "reporter": "epdg"
        },
        {
          "receiver": "epdg",
          "name": "ike_auth_3_response",
          "reporter": "ims"
        },
        {
          "receiver": "ims",
          "name": "401_unauthorized",
          "reporter": "ims",
          "sub": [
            {
              "name": "www_authenticate",
              "sub": [
                {
                  "name": "nonce",
                  "op": "update",
                  "type": "string",
                  "value": "random"
                }
              ]
            }
          ]
        }
      ]
    },
    {
      "testcase": [
        {
          "receiver": "ue",
          "name": "enable_vowifi",
          "reporter": "epdg",
          "id": "update-401_unauthorized-www_authenticate-nonce-min-2"
        },
        {
          "receiver": "epdg",
          "name": "ike_sa_init_response",
          "reporter": "epdg"
        },
        {
          "receiver": "epdg",
          "name": "ike_auth_1_response",
          "reporter": "epdg"
        },
        {
          "receiver": "epdg",
          "name": "ike_auth_2_response",
          "reporter": "epdg"
        },
        {
          "receiver": "epdg",
          "name": "ike_auth_3_response",
          "reporter": "ims"
        },
        {
          "receiver": "ims",
          "name": "401_unauthorized",
          "reporter": "ims",
          "sub": [
            {
              "name": "www_authenticate",
              "sub": [
                {
                  "name": "nonce",
                  "op": "update",
                  "type": "string",
                  "value": "min"
                }
              ]
            }
          ]
        }
      ]
    },
    {
      "testcase": [
        {
          "receiver": "ue",
          "name": "enable_vowifi",
          "reporter": "epdg",
          "id": "update-401_unauthorized-www_authenticate-nonce-median-3"
        },
        {
          "receiver": "epdg",
          "name": "ike_sa_init_response",
          "reporter": "epdg"
        },
        {
          "receiver": "epdg",
          "name": "ike_auth_1_response",
          "reporter": "epdg"
        },
        {
          "receiver": "epdg",
          "name": "ike_auth_2_response",
          "reporter": "epdg"
        },
        {
          "receiver": "epdg",
          "name": "ike_auth_3_response",
          "reporter": "ims"
        },
        {
          "receiver": "ims",
          "name": "401_unauthorized",
          "reporter": "ims",
          "sub": [
            {
              "name": "www_authenticate",
              "sub": [
                {
                  "name": "nonce",
                  "op": "update",
                  "type": "string",
                  "value": "median"
                }
              ]
            }
          ]
        }
      ]
    },
    {
      "testcase": [
        {
          "receiver": "ue",
          "name": "enable_vowifi",
          "reporter": "epdg",
          "id": "update-401_unauthorized-www_authenticate-nonce-mean-4"
        },
        {
          "receiver": "epdg",
          "name": "ike_sa_init_response",
          "reporter": "epdg"
        },
        {
          "receiver": "epdg",
          "name": "ike_auth_1_response",
          "reporter": "epdg"
        },
        {
          "receiver": "epdg",
          "name": "ike_auth_2_response",
          "reporter": "epdg"
        },
        {
          "receiver": "epdg",
          "name": "ike_auth_3_response",
          "reporter": "ims"
        },
        {
          "receiver": "ims",
          "name": "401_unauthorized",
          "reporter": "ims",
          "sub": [
            {
              "name": "www_authenticate",
              "sub": [
                {
                  "name": "nonce",
                  "op": "update",
                  "type": "string",
                  "value": "mean"
                }
              ]
            }
          ]
        }
      ]
    },
    {
      "testcase": [
        {
          "receiver": "ue",
          "name": "enable_vowifi",
          "reporter": "epdg",
          "id": "update-401_unauthorized-www_authenticate-nonce-max-5"
        },
        {
          "receiver": "epdg",
          "name": "ike_sa_init_response",
          "reporter": "epdg"
        },
        {
          "receiver": "epdg",
          "name": "ike_auth_1_response",
          "reporter": "epdg"
        },
        {
          "receiver": "epdg",
          "name": "ike_auth_2_response",
          "reporter": "epdg"
        },
        {
          "receiver": "epdg",
          "name": "ike_auth_3_response",
          "reporter": "ims"
        },
        {
          "receiver": "ims",
          "name": "401_unauthorized",
          "reporter": "ims",
          "sub": [
            {
              "name": "www_authenticate",
              "sub": [
                {
                  "name": "nonce",
                  "op": "update",
                  "type": "string",
                  "value": "max"
                }
              ]
            }
          ]
        }
      ]
    },
    {
      "testcase": [
        {
          "receiver": "ue",
          "name": "enable_vowifi",
          "reporter": "epdg",
          "id": "update-401_unauthorized-www_authenticate-algorithm-random-1"
        },
        {
          "receiver": "epdg",
          "name": "ike_sa_init_response",
          "reporter": "epdg"
        },
        {
          "receiver": "epdg",
          "name": "ike_auth_1_response",
          "reporter": "epdg"
        },
        {
          "receiver": "epdg",
          "name": "ike_auth_2_response",
          "reporter": "epdg"
        },
        {
          "receiver": "epdg",
          "name": "ike_auth_3_response",
          "reporter": "ims"
        },
        {
          "receiver": "ims",
          "name": "401_unauthorized",
          "reporter": "ims",
          "sub": [
            {
              "name": "www_authenticate",
              "sub": [
                {
                  "name": "algorithm",
                  "op": "update",
                  "type": "string",
                  "value": "random"
                }
              ]
            }
          ]
        }
      ]
    },
    {
      "testcase": [
        {
          "receiver": "ue",
          "name": "enable_vowifi",
          "reporter": "epdg",
          "id": "update-401_unauthorized-www_authenticate-algorithm-min-2"
        },
        {
          "receiver": "epdg",
          "name": "ike_sa_init_response",
          "reporter": "epdg"
        },
        {
          "receiver": "epdg",
          "name": "ike_auth_1_response",
          "reporter": "epdg"
        },
        {
          "receiver": "epdg",
          "name": "ike_auth_2_response",
          "reporter": "epdg"
        },
        {
          "receiver": "epdg",
          "name": "ike_auth_3_response",
          "reporter": "ims"
        },
        {
          "receiver": "ims",
          "name": "401_unauthorized",
          "reporter": "ims",
          "sub": [
            {
              "name": "www_authenticate",
              "sub": [
                {
                  "name": "algorithm",
                  "op": "update",
                  "type": "string",
                  "value": "min"
                }
              ]
            }
          ]
        }
      ]
    },
    {
      "testcase": [
        {
          "receiver": "ue",
          "name": "enable_vowifi",
          "reporter": "epdg",
          "id": "update-401_unauthorized-www_authenticate-algorithm-median-3"
        },
        {
          "receiver": "epdg",
          "name": "ike_sa_init_response",
          "reporter": "epdg"
        },
        {
          "receiver": "epdg",
          "name": "ike_auth_1_response",
          "reporter": "epdg"
        },
        {
          "receiver": "epdg",
          "name": "ike_auth_2_response",
          "reporter": "epdg"
        },
        {
          "receiver": "epdg",
          "name": "ike_auth_3_response",
          "reporter": "ims"
        },
        {
          "receiver": "ims",
          "name": "401_unauthorized",
          "reporter": "ims",
          "sub": [
            {
              "name": "www_authenticate",
              "sub": [
                {
                  "name": "algorithm",
                  "op": "update",
                  "type": "string",
                  "value": "median"
                }
              ]
            }
          ]
        }
      ]
    },
    {
      "testcase": [
        {
          "receiver": "ue",
          "name": "enable_vowifi",
          "reporter": "epdg",
          "id": "update-401_unauthorized-www_authenticate-algorithm-mean-4"
        },
        {
          "receiver": "epdg",
          "name": "ike_sa_init_response",
          "reporter": "epdg"
        },
        {
          "receiver": "epdg",
          "name": "ike_auth_1_response",
          "reporter": "epdg"
        },
        {
          "receiver": "epdg",
          "name": "ike_auth_2_response",
          "reporter": "epdg"
        },
        {
          "receiver": "epdg",
          "name": "ike_auth_3_response",
          "reporter": "ims"
        },
        {
          "receiver": "ims",
          "name": "401_unauthorized",
          "reporter": "ims",
          "sub": [
            {
              "name": "www_authenticate",
              "sub": [
                {
                  "name": "algorithm",
                  "op": "update",
                  "type": "string",
                  "value": "mean"
                }
              ]
            }
          ]
        }
      ]
    },
    {
      "testcase": [
        {
          "receiver": "ue",
          "name": "enable_vowifi",
          "reporter": "epdg",
          "id": "update-401_unauthorized-www_authenticate-algorithm-max-5"
        },
        {
          "receiver": "epdg",
          "name": "ike_sa_init_response",
          "reporter": "epdg"
        },
        {
          "receiver": "epdg",
          "name": "ike_auth_1_response",
          "reporter": "epdg"
        },
        {
          "receiver": "epdg",
          "name": "ike_auth_2_response",
          "reporter": "epdg"
        },
        {
          "receiver": "epdg",
          "name": "ike_auth_3_response",
          "reporter": "ims"
        },
        {
          "receiver": "ims",
          "name": "401_unauthorized",
          "reporter": "ims",
          "sub": [
            {
              "name": "www_authenticate",
              "sub": [
                {
                  "name": "algorithm",
                  "op": "update",
                  "type": "string",
                  "value": "max"
                }
              ]
            }
          ]
        }
      ]
    },
    {
      "testcase": [
        {
          "receiver": "ue",
          "name": "enable_vowifi",
          "reporter": "epdg",
          "id": "update-401_unauthorized-security_server-alg-random-1"
        },
        {
          "receiver": "epdg",
          "name": "ike_sa_init_response",
          "reporter": "epdg"
        },
        {
          "receiver": "epdg",
          "name": "ike_auth_1_response",
          "reporter": "epdg"
        },
        {
          "receiver": "epdg",
          "name": "ike_auth_2_response",
          "reporter": "epdg"
        },
        {
          "receiver": "epdg",
          "name": "ike_auth_3_response",
          "reporter": "ims"
        },
        {
          "receiver": "ims",
          "name": "401_unauthorized",
          "reporter": "ims",
          "sub": [
            {
              "name": "security_server",
              "sub": [
                {
                  "name": "alg",
                  "op": "update",
                  "type": "string",
                  "value": "random"
                }
              ]
            }
          ]
        }
      ]
    },
    {
      "testcase": [
        {
          "receiver": "ue",
          "name": "enable_vowifi",
          "reporter": "epdg",
          "id": "update-401_unauthorized-security_server-alg-min-2"
        },
        {
          "receiver": "epdg",
          "name": "ike_sa_init_response",
          "reporter": "epdg"
        },
        {
          "receiver": "epdg",
          "name": "ike_auth_1_response",
          "reporter": "epdg"
        },
        {
          "receiver": "epdg",
          "name": "ike_auth_2_response",
          "reporter": "epdg"
        },
        {
          "receiver": "epdg",
          "name": "ike_auth_3_response",
          "reporter": "ims"
        },
        {
          "receiver": "ims",
          "name": "401_unauthorized",
          "reporter": "ims",
          "sub": [
            {
              "name": "security_server",
              "sub": [
                {
                  "name": "alg",
                  "op": "update",
                  "type": "string",
                  "value": "min"
                }
              ]
            }
          ]
        }
      ]
    },
    {
      "testcase": [
        {
          "receiver": "ue",
          "name": "enable_vowifi",
          "reporter": "epdg",
          "id": "update-401_unauthorized-security_server-alg-median-3"
        },
        {
          "receiver": "epdg",
          "name": "ike_sa_init_response",
          "reporter": "epdg"
        },
        {
          "receiver": "epdg",
          "name": "ike_auth_1_response",
          "reporter": "epdg"
        },
        {
          "receiver": "epdg",
          "name": "ike_auth_2_response",
          "reporter": "epdg"
        },
        {
          "receiver": "epdg",
          "name": "ike_auth_3_response",
          "reporter": "ims"
        },
        {
          "receiver": "ims",
          "name": "401_unauthorized",
          "reporter": "ims",
          "sub": [
            {
              "name": "security_server",
              "sub": [
                {
                  "name": "alg",
                  "op": "update",
                  "type": "string",
                  "value": "median"
                }
              ]
            }
          ]
        }
      ]
    },
    {
      "testcase": [
        {
          "receiver": "ue",
          "name": "enable_vowifi",
          "reporter": "epdg",
          "id": "update-401_unauthorized-security_server-alg-mean-4"
        },
        {
          "receiver": "epdg",
          "name": "ike_sa_init_response",
          "reporter": "epdg"
        },
        {
          "receiver": "epdg",
          "name": "ike_auth_1_response",
          "reporter": "epdg"
        },
        {
          "receiver": "epdg",
          "name": "ike_auth_2_response",
          "reporter": "epdg"
        },
        {
          "receiver": "epdg",
          "name": "ike_auth_3_response",
          "reporter": "ims"
        },
        {
          "receiver": "ims",
          "name": "401_unauthorized",
          "reporter": "ims",
          "sub": [
            {
              "name": "security_server",
              "sub": [
                {
                  "name": "alg",
                  "op": "update",
                  "type": "string",
                  "value": "mean"
                }
              ]
            }
          ]
        }
      ]
    },
    {
      "testcase": [
        {
          "receiver": "ue",
          "name": "enable_vowifi",
          "reporter": "epdg",
          "id": "update-401_unauthorized-security_server-alg-max-5"
        },
        {
          "receiver": "epdg",
          "name": "ike_sa_init_response",
          "reporter": "epdg"
        },
        {
          "receiver": "epdg",
          "name": "ike_auth_1_response",
          "reporter": "epdg"
        },
        {
          "receiver": "epdg",
          "name": "ike_auth_2_response",
          "reporter": "epdg"
        },
        {
          "receiver": "epdg",
          "name": "ike_auth_3_response",
          "reporter": "ims"
        },
        {
          "receiver": "ims",
          "name": "401_unauthorized",
          "reporter": "ims",
          "sub": [
            {
              "name": "security_server",
              "sub": [
                {
                  "name": "alg",
                  "op": "update",
                  "type": "string",
                  "value": "max"
                }
              ]
            }
          ]
        }
      ]
    },
    {
      "testcase": [
        {
          "receiver": "ue",
          "name": "enable_vowifi",
          "reporter": "epdg",
          "id": "update-401_unauthorized-security_server-ealg-random-1"
        },
        {
          "receiver": "epdg",
          "name": "ike_sa_init_response",
          "reporter": "epdg"
        },
        {
          "receiver": "epdg",
          "name": "ike_auth_1_response",
          "reporter": "epdg"
        },
        {
          "receiver": "epdg",
          "name": "ike_auth_2_response",
          "reporter": "epdg"
        },
        {
          "receiver": "epdg",
          "name": "ike_auth_3_response",
          "reporter": "ims"
        },
        {
          "receiver": "ims",
          "name": "401_unauthorized",
          "reporter": "ims",
          "sub": [
            {
              "name": "security_server",
              "sub": [
                {
                  "name": "ealg",
                  "op": "update",
                  "type": "string",
                  "value": "random"
                }
              ]
            }
          ]
        }
      ]
    },
    {
      "testcase": [
        {
          "receiver": "ue",
          "name": "enable_vowifi",
          "reporter": "epdg",
          "id": "update-401_unauthorized-security_server-ealg-min-2"
        },
        {
          "receiver": "epdg",
          "name": "ike_sa_init_response",
          "reporter": "epdg"
        },
        {
          "receiver": "epdg",
          "name": "ike_auth_1_response",
          "reporter": "epdg"
        },
        {
          "receiver": "epdg",
          "name": "ike_auth_2_response",
          "reporter": "epdg"
        },
        {
          "receiver": "epdg",
          "name": "ike_auth_3_response",
          "reporter": "ims"
        },
        {
          "receiver": "ims",
          "name": "401_unauthorized",
          "reporter": "ims",
          "sub": [
            {
              "name": "security_server",
              "sub": [
                {
                  "name": "ealg",
                  "op": "update",
                  "type": "string",
                  "value": "min"
                }
              ]
            }
          ]
        }
      ]
    },
    {
      "testcase": [
        {
          "receiver": "ue",
          "name": "enable_vowifi",
          "reporter": "epdg",
          "id": "update-401_unauthorized-security_server-ealg-median-3"
        },
        {
          "receiver": "epdg",
          "name": "ike_sa_init_response",
          "reporter": "epdg"
        },
        {
          "receiver": "epdg",
          "name": "ike_auth_1_response",
          "reporter": "epdg"
        },
        {
          "receiver": "epdg",
          "name": "ike_auth_2_response",
          "reporter": "epdg"
        },
        {
          "receiver": "epdg",
          "name": "ike_auth_3_response",
          "reporter": "ims"
        },
        {
          "receiver": "ims",
          "name": "401_unauthorized",
          "reporter": "ims",
          "sub": [
            {
              "name": "security_server",
              "sub": [
                {
                  "name": "ealg",
                  "op": "update",
                  "type": "string",
                  "value": "median"
                }
              ]
            }
          ]
        }
      ]
    },
    {
      "testcase": [
        {
          "receiver": "ue",
          "name": "enable_vowifi",
          "reporter": "epdg",
          "id": "update-401_unauthorized-security_server-ealg-mean-4"
        },
        {
          "receiver": "epdg",
          "name": "ike_sa_init_response",
          "reporter": "epdg"
        },
        {
          "receiver": "epdg",
          "name": "ike_auth_1_response",
          "reporter": "epdg"
        },
        {
          "receiver": "epdg",
          "name": "ike_auth_2_response",
          "reporter": "epdg"
        },
        {
          "receiver": "epdg",
          "name": "ike_auth_3_response",
          "reporter": "ims"
        },
        {
          "receiver": "ims",
          "name": "401_unauthorized",
          "reporter": "ims",
          "sub": [
            {
              "name": "security_server",
              "sub": [
                {
                  "name": "ealg",
                  "op": "update",
                  "type": "string",
                  "value": "mean"
                }
              ]
            }
          ]
        }
      ]
    },
    {
      "testcase": [
        {
          "receiver": "ue",
          "name": "enable_vowifi",
          "reporter": "epdg",
          "id": "update-401_unauthorized-security_server-ealg-max-5"
        },
        {
          "receiver": "epdg",
          "name": "ike_sa_init_response",
          "reporter": "epdg"
        },
        {
          "receiver": "epdg",
          "name": "ike_auth_1_response",
          "reporter": "epdg"
        },
        {
          "receiver": "epdg",
          "name": "ike_auth_2_response",
          "reporter": "epdg"
        },
        {
          "receiver": "epdg",
          "name": "ike_auth_3_response",
          "reporter": "ims"
        },
        {
          "receiver": "ims",
          "name": "401_unauthorized",
          "reporter": "ims",
          "sub": [
            {
              "name": "security_server",
              "sub": [
                {
                  "name": "ealg",
                  "op": "update",
                  "type": "string",
                  "value": "max"
                }
              ]
            }
          ]
        }
      ]
    },
    {
      "testcase": [
        {
          "receiver": "ue",
          "name": "enable_vowifi",
          "reporter": "epdg",
          "id": "drop-401_unauthorized-www_authenticate-nonce-1"
        },
        {
          "receiver": "epdg",
          "name": "ike_sa_init_response",
          "reporter": "epdg"
        },
        {
          "receiver": "epdg",
          "name": "ike_auth_1_response",
          "reporter": "epdg"
        },
        {
          "receiver": "epdg",
          "name": "ike_auth_2_response",
          "reporter": "epdg"
        },
        {
          "receiver": "epdg",
          "name": "ike_auth_3_response",
          "reporter": "ims"
        },
        {
          "receiver": "ims",
          "name": "401_unauthorized",
          "reporter": "ims",
          "sub": [
            {
              "name": "www_authenticate",
              "sub": [
                {
                  "name": "nonce",
                  "op": "drop",
                  "type": "string",
                  "value": "max"
                }
              ]
            }
          ]
        }
      ]
    },
    {
      "testcase": [
        {
          "receiver": "ue",
          "name": "enable_vowifi",
          "reporter": "epdg",
          "id": "drop-401_unauthorized-www_authenticate-algorithm-1"
        },
        {
          "receiver": "epdg",
          "name": "ike_sa_init_response",
          "reporter": "epdg"
        },
        {
          "receiver": "epdg",
          "name": "ike_auth_1_response",
          "reporter": "epdg"
        },
        {
          "receiver": "epdg",
          "name": "ike_auth_2_response",
          "reporter": "epdg"
        },
        {
          "receiver": "epdg",
          "name": "ike_auth_3_response",
          "reporter": "ims"
        },
        {
          "receiver": "ims",
          "name": "401_unauthorized",
          "reporter": "ims",
          "sub": [
            {
              "name": "www_authenticate",
              "sub": [
                {
                  "name": "algorithm",
                  "op": "drop",
                  "type": "string",
                  "value": "max"
                }
              ]
            }
          ]
        }
      ]
    },
    {
      "testcase": [
        {
          "receiver": "ue",
          "name": "enable_vowifi",
          "reporter": "epdg",
          "id": "drop-401_unauthorized-security_server-alg-1"
        },
        {
          "receiver": "epdg",
          "name": "ike_sa_init_response",
          "reporter": "epdg"
        },
        {
          "receiver": "epdg",
          "name": "ike_auth_1_response",
          "reporter": "epdg"
        },
        {
          "receiver": "epdg",
          "name": "ike_auth_2_response",
          "reporter": "epdg"
        },
        {
          "receiver": "epdg",
          "name": "ike_auth_3_response",
          "reporter": "ims"
        },
        {
          "receiver": "ims",
          "name": "401_unauthorized",
          "reporter": "ims",
          "sub": [
            {
              "name": "security_server",
              "sub": [
                {
                  "name": "alg",
                  "op": "drop",
                  "type": "string",
                  "value": "max"
                }
              ]
            }
          ]
        }
      ]
    },
    {
      "testcase": [
        {
          "receiver": "ue",
          "name": "enable_vowifi",
          "reporter": "epdg",
          "id": "drop-401_unauthorized-security_server-ealg-1"
        },
        {
          "receiver": "epdg",
          "name": "ike_sa_init_response",
          "reporter": "epdg"
        },
        {
          "receiver": "epdg",
          "name": "ike_auth_1_response",
          "reporter": "epdg"
        },
        {
          "receiver": "epdg",
          "name": "ike_auth_2_response",
          "reporter": "epdg"
        },
        {
          "receiver": "epdg",
          "name": "ike_auth_3_response",
          "reporter": "ims"
        },
        {
          "receiver": "ims",
          "name": "401_unauthorized",
          "reporter": "ims",
          "sub": [
            {
              "name": "security_server",
              "sub": [
                {
                  "name": "ealg",
                  "op": "drop",
                  "type": "string",
                  "value": "max"
                }
              ]
            }
          ]
        }
      ]
    }
  ]
}