{
  "testcases": [
    {
      "testcase": [
        {
          "receiver": "ue",
          "name": "enable_vowifi",
          "sender": "epdg",
          "id": "auth-1-invalid-message-size"
        },
        {
          "receiver": "epdg",
          "name": "ike_sa_init_response",
          "sender": "epdg"
        },
        {
          "receiver": "epdg",
          "name": "ike_auth_1_response",
          "sender": "epdg",
          "sub": [
            {
              "name": "message_size",
              "op": "update",
              "type": "uint16",
              "value": 4000
            }
          ]
        }
      ]
    }
  ]
}
